rtl/data_memory.sv

`timescale 1ns/1ps

module data_memory(

    input  logic        clk,

    input  logic        reset,


    input  logic        mem_read,

    input  logic        mem_write,


    input  logic [15:0] address,

    input  logic [15:0] write_data,


    output logic [15:0] read_data

);



logic [15:0] memory [0:255];


integer i;



// Memory Write and Reset

always_ff @(posedge clk or posedge reset)

begin


    if(reset)

    begin

        for(i=0;i<256;i=i+1)

        begin

            memory[i] <= 16'd0;

        end

    end


    else

    begin


        if(mem_write)

        begin

            memory[address] <= write_data;

        end


    end


end



// Memory Read

always_comb

begin


    if(mem_read)

    begin

        read_data = memory[address];

    end


    else

    begin

        read_data = 16'd0;

    end


end



endmodule

alu.sv

`timescale 1ns/1ps

module alu(

    input  logic [15:0] operand_a,

    input  logic [15:0] operand_b,

    input  logic [3:0]  alu_control,


    output logic [15:0] alu_result,

    output logic zero_flag

);


// ALU Operations

always_comb
begin

    case(alu_control)


        // ADD

        4'b0000:

        begin
            alu_result = operand_a + operand_b;
        end



        // SUB

        4'b0001:

        begin
            alu_result = operand_a - operand_b;
        end



        // AND

        4'b0010:

        begin
            alu_result = operand_a & operand_b;
        end



        // OR

        4'b0011:

        begin
            alu_result = operand_a | operand_b;
        end



        // XOR

        4'b0100:

        begin
            alu_result = operand_a ^ operand_b;
        end



        // SHIFT LEFT

        4'b0101:

        begin
            alu_result = operand_a << operand_b[3:0];
        end



        // SHIFT RIGHT

        4'b0110:

        begin
            alu_result = operand_a >> operand_b[3:0];
        end



        // COMPARE

        4'b0111:

        begin
            if(operand_a == operand_b)

                alu_result = 16'd0;

            else

                alu_result = 16'd1;

        end



        // DEFAULT

        default:

        begin
            alu_result = 16'd0;
        end


    endcase


end



// Zero Flag Generation

always_comb
begin

    if(alu_result == 16'd0)

        zero_flag = 1'b1;

    else

        zero_flag = 1'b0;


end


endmodule

mux.sv

`timescale 1ns/1ps

module mux(

    input  logic [15:0] input0,

    input  logic [15:0] input1,


    input  logic select,


    output logic [15:0] output_data

);


// 2x1 Multiplexer

always_comb

begin


    case(select)


        1'b0:

        begin

            output_data = input0;

        end



        1'b1:

        begin

            output_data = input1;

        end



        default:

        begin

            output_data = 16'd0;

        end


    endcase


end



endmodule

immediate_generator.sv



`timescale 1ns/1ps

module immediate_generator(

    input  logic [15:0] instruction,

    output logic [15:0] immediate

);


// Immediate value generation

always_comb

begin


    // Extract lower 8 bits

    if(instruction[7] == 1'b1)

    begin

        // Sign extension for negative value

        immediate = {8'hFF, instruction[7:0]};

    end


    else

    begin

        // Zero extension for positive value

        immediate = {8'h00, instruction[7:0]};

    end


end



endmodule

register_file.sv

`timescale 1ns/1ps

module register_file(

    input  logic        clk,

    input  logic        reset,


    input  logic        reg_write,


    input  logic [3:0]  read_addr1,

    input  logic [3:0]  read_addr2,


    input  logic [3:0]  write_addr,


    input  logic [15:0] write_data,


    output logic [15:0] read_data1,

    output logic [15:0] read_data2

);



logic [15:0] registers [0:15];


integer i;



// Register Reset and Write Operation

always_ff @(posedge clk or posedge reset)

begin


    if(reset)

    begin

        for(i=0;i<16;i=i+1)

        begin

            registers[i] <= 16'd0;

        end

    end


    else

    begin


        if(reg_write)

        begin


            // R0 always remains zero

            if(write_addr != 4'd0)

            begin

                registers[write_addr] <= write_data;

            end


        end


    end


end



// Register Read Operation

always_comb
begin
    if(read_addr1 < 16)
        read_data1 = registers[read_addr1];
    else
        read_data1 = 16'd0;

    if(read_addr2 < 16)
        read_data2 = registers[read_addr2];
    else
        read_data2 = 16'd0;
end



endmodule

rtl/control_unit.sv

`timescale 1ns/1ps

module control_unit(

    input  logic [3:0] opcode,


    output logic [3:0] alu_control,

    output logic reg_write,

    output logic mem_read,

    output logic mem_write,
    output logic alu_src,
    output logic jump,

    output logic branch

);


// Opcode Decode

always_comb
begin


    // Default values

    alu_control = 4'b0000;

    reg_write   = 1'b0;

    mem_read    = 1'b0;

    mem_write   = 1'b0;
    alu_src     = 1'b0;
    jump        = 1'b0;

    branch      = 1'b0;



    case(opcode)



        // ADD
        4'b0000:

        begin

            alu_control = 4'b0000;

            reg_write = 1'b1;

        end



        // SUB
        4'b0001:

        begin

            alu_control = 4'b0001;

            reg_write = 1'b1;

        end



        // AND
        4'b0010:

        begin

            alu_control = 4'b0010;

            reg_write = 1'b1;

        end



        // OR
        4'b0011:

        begin

            alu_control = 4'b0011;

            reg_write = 1'b1;

        end



        // XOR
        4'b0100:

        begin

            alu_control = 4'b0100;

            reg_write = 1'b1;

        end



        // LOAD
        4'b0101:

        begin

            alu_control = 4'b0000;
            alu_src  = 1'b1;
            mem_read = 1'b1;

            reg_write = 1'b1;

        end



        // STORE
        4'b0110:

        begin

            alu_control = 4'b0000;
            alu_src   = 1'b1;
            mem_write = 1'b1;

        end



        // MOV
        4'b0111:

        begin

            alu_control = 4'b0000;

            reg_write = 1'b1;

        end



        // JUMP
        4'b1000:

        begin

            jump = 1'b1;

        end



        // BEQ
        4'b1001:

        begin

            branch = 1'b1;

            alu_control = 4'b0001;

        end



        // BNE
        4'b1010:

        begin

            branch = 1'b1;

            alu_control = 4'b0001;

        end



        // SHIFT LEFT
        4'b1011:

        begin

            alu_control = 4'b0101;

            reg_write = 1'b1;

        end



        // SHIFT RIGHT
        4'b1100:

        begin

            alu_control = 4'b0110;

            reg_write = 1'b1;

        end



        default:

        begin

            alu_control = 4'b0000;

            reg_write = 1'b0;

            mem_read = 1'b0;

            mem_write = 1'b0;

            jump = 1'b0;

            branch = 1'b0;

        end


    endcase


end


endmodule

rtl/instruction_memory.sv
`timescale 1ns/1ps

module instruction_memory(

    input  logic [15:0] address,
    output logic [15:0] instruction

);

logic [15:0] memory [0:255];

integer i;

initial begin

    memory[0] = 16'h0123;
    memory[1] = 16'h1456;
    memory[2] = 16'h2678;
    memory[3] = 16'h389A;
    memory[4] = 16'h4ABC;

    for(i=5; i<256; i=i+1)
        memory[i] = 16'h0000;

    $display("MEM0=%h", memory[0]);
    $display("MEM1=%h", memory[1]);
    $display("MEM2=%h", memory[2]);

end

always_comb begin

    instruction = memory[address >> 1];

end

endmodule

program_counter.sv
`timescale 1ns/1ps

module program_counter(

    input  logic clk,
    input  logic reset,
    input  logic pc_enable,
    input  logic [15:0] pc_next,
    output logic [15:0] pc

);

always_ff @(posedge clk or posedge reset)
begin
    if(reset)
        pc <= 16'h0000;

    else if(pc_enable)
        pc <= pc_next;

end

endmodule

rtl/cpu_top.sv

`timescale 1ns/1ps

module cpu_top(
    input  logic clk,
    input  logic reset,
    output logic [15:0] pc_out,
    output logic [15:0] instruction_out,
    output logic [15:0] alu_result_out
);


//==============================
// Program Counter
//==============================

logic [15:0] pc;
logic [15:0] pc_next;
logic [15:0] instruction_address;

assign pc_next = pc + 16'd2;

assign instruction_address = pc >> 1;



program_counter PC_UNIT(

    .clk(clk),
    .reset(reset),
    .pc_enable(1'b1),
    .pc_next(pc_next),
    .pc(pc)

);



//==============================
// Instruction Memory
//==============================

 logic [15:0] instruction;



instruction_memory IM_UNIT(

    .address(instruction_address),
    .instruction(instruction)

);



//==============================
// Instruction Fields
//==============================

logic [3:0] opcode;
logic [3:0] rd;
logic [3:0] rs1;
logic [3:0] rs2;


assign opcode = instruction[15:12];

assign rd  = instruction[11:8];

assign rs1 = instruction[7:4];

assign rs2 = instruction[3:0];



//==============================
// Control Unit
//==============================

logic [3:0] alu_control;

logic reg_write;
logic mem_read;
logic mem_write;
logic alu_src;
logic jump;
logic branch;



control_unit CU_UNIT(

    .opcode(opcode),

    .alu_control(alu_control),

    .reg_write(reg_write),

    .mem_read(mem_read),

    .mem_write(mem_write),
    .alu_src(alu_src),
    .jump(jump),

    .branch(branch)

);



//==============================
// Register File
//==============================


logic [15:0] read_data1;
logic [15:0] read_data2;

logic [15:0] write_back_data;



register_file RF_UNIT(

    .clk(clk),

    .reset(reset),

    .reg_write(reg_write),

    .read_addr1(rs1),

    .read_addr2(rs2),

    .write_addr(rd),

    .write_data(write_back_data),

    .read_data1(read_data1),

    .read_data2(read_data2)

);



//==============================
// Immediate Generator
//==============================

logic [15:0] immediate;



immediate_generator IMM_UNIT(

    .instruction(instruction),

    .immediate(immediate)

);



//==============================
// ALU Input MUX
//==============================

logic [15:0] alu_input2;



mux MUX_UNIT(

    .input0(read_data2),

    .input1(immediate),

    .select(alu_src),

    .output_data(alu_input2)

);



//==============================
// ALU
//==============================

logic [15:0] alu_result;

logic zero_flag;



alu ALU_UNIT(

    .operand_a(read_data1),

    .operand_b(alu_input2),

    .alu_control(alu_control),

    .alu_result(alu_result),

    .zero_flag(zero_flag)

);



//==============================
// Data Memory
//==============================
logic [15:0] address;
logic [15:0] write_data;
logic [15:0] memory_read_data;

assign address    = alu_result;
assign write_data = read_data2;



data_memory DM_UNIT(
    .clk(clk),
    .mem_read(mem_read),
    .mem_write(mem_write),
    .address(address),
    .write_data(write_data),
    .read_data(memory_read_data)
);


//==============================
// Write Back MUX
//==============================


always_comb
begin

    if(mem_read)

        write_back_data = memory_read_data;

    else

        write_back_data = alu_result;


end
assign pc_out = pc;
assign instruction_out = instruction;
assign alu_result_out = alu_result;


endmodule

tb/cpu_tb.sv
`timescale 1ns/1ps

module cpu_tb;

    logic clk;
    logic reset;

    cpu_top DUT (
        .clk(clk),
        .reset(reset)
    );

    // Clock
    initial begin
        clk = 1'b0;
    end

    always #5 clk = ~clk;

    // Reset
    initial begin
        reset = 1'b1;
        #20;
        reset = 1'b0;
    end

    // Waveform
    initial begin
        $dumpfile("cpu_waveform.vcd");
        $dumpvars(0, cpu_tb);
    end

endmodule

16bir_RISC_Processer/16bir_RISC_Processer.sim/sim_1/behav/xsim/cpu_waveform.vcd
$date
   Wed Sep  9 14:21:59 2026
$end
$version
  2018.2
$end
$timescale
  1ps
$end
$scope module cpu_tb $end
$var reg 1 ! clk $end
$var reg 1 " reset $end
$scope module DUT $end
$var wire 1 # clk $end
$var wire 1 $ reset $end
$var reg 16 % pc_out [15:0] $end
$var reg 16 & instruction_out [15:0] $end
$var reg 16 ' alu_result_out [15:0] $end
$var reg 16 ( pc [15:0] $end
$var reg 16 ) pc_next [15:0] $end
$var reg 16 * instruction_address [15:0] $end
$var reg 16 + instruction [15:0] $end
$var reg 4 , opcode [3:0] $end
$var reg 4 - rd [3:0] $end
$var reg 4 . rs1 [3:0] $end
$var reg 4 / rs2 [3:0] $end
$var reg 4 0 alu_control [3:0] $end
$var reg 1 1 reg_write $end
$var reg 1 2 mem_read $end
$var reg 1 3 mem_write $end
$var reg 1 4 alu_src $end
$var reg 1 5 jump $end
$var reg 1 6 branch $end
$var reg 16 7 read_data1 [15:0] $end
$var reg 16 8 read_data2 [15:0] $end
$var reg 16 9 write_back_data [15:0] $end
$var reg 16 : immediate [15:0] $end
$var reg 16 ; alu_input2 [15:0] $end
$var reg 16 < alu_result [15:0] $end
$var reg 1 = zero_flag $end
$var reg 16 > address [15:0] $end
$var reg 16 ? write_data [15:0] $end
$var reg 16 @ memory_read_data [15:0] $end
$scope module PC_UNIT $end
$var wire 1 # clk $end
$var wire 1 $ reset $end
$var wire 1 A pc_enable $end
$var wire 16 B pc_next [15:0] $end
$var reg 16 ( pc [15:0] $end
$upscope $end
$scope module IM_UNIT $end
$var wire 16 C address [15:0] $end
$var reg 16 + instruction [15:0] $end
$var integer 32 D i $end
$upscope $end
$scope module CU_UNIT $end
$var wire 4 E opcode [3:0] $end
$var reg 4 0 alu_control [3:0] $end
$var reg 1 1 reg_write $end
$var reg 1 2 mem_read $end
$var reg 1 3 mem_write $end
$var reg 1 4 alu_src $end
$var reg 1 5 jump $end
$var reg 1 6 branch $end
$upscope $end
$scope module RF_UNIT $end
$var wire 1 # clk $end
$var wire 1 $ reset $end
$var wire 1 F reg_write $end
$var wire 4 G read_addr1 [3:0] $end
$var wire 4 H read_addr2 [3:0] $end
$var wire 4 I write_addr [3:0] $end
$var wire 16 J write_data [15:0] $end
$var reg 16 7 read_data1 [15:0] $end
$var reg 16 8 read_data2 [15:0] $end
$var integer 32 K i $end
$upscope $end
$scope module IMM_UNIT $end
$var wire 16 L instruction [15:0] $end
$var reg 16 : immediate [15:0] $end
$upscope $end
$scope module MUX_UNIT $end
$var wire 16 M input0 [15:0] $end
$var wire 16 N input1 [15:0] $end
$var wire 1 O select $end
$var reg 16 ; output_data [15:0] $end
$upscope $end
$scope module ALU_UNIT $end
$var wire 16 P operand_a [15:0] $end
$var wire 16 Q operand_b [15:0] $end
$var wire 4 R alu_control [3:0] $end
$var reg 16 < alu_result [15:0] $end
$var reg 1 = zero_flag $end
$upscope $end
$scope module DM_UNIT $end
$var wire 1 # clk $end
$var wire 1 S reset $end
$var wire 1 T mem_read $end
$var wire 1 U mem_write $end
$var wire 16 V address [15:0] $end
$var wire 16 W write_data [15:0] $end
$var reg 16 @ read_data [15:0] $end
$var integer 32 X i $end
$upscope $end
$upscope $end
$upscope $end
$enddefinitions $end
#0
$dumpvars
0!
1"
0#
1$
b0 %
b100100011 &
b0 '
b0 (
b10 )
b0 *
b100100011 +
b0 ,
b1 -
b10 .
b11 /
b0 0
11
02
03
04
05
06
b0 7
b0 8
b0 9
b100011 :
b0 ;
b0 <
1=
b0 >
b0 ?
b0 @
1A
b10 B
b0 C
b100000000 D
b0 E
1F
b10 G
b11 H
b1 I
b0 J
bx K
b100100011 L
b0 M
b100011 N
0O
b0 P
b0 Q
b0 R
zS
0T
0U
b0 V
b0 W
bx X
$end
#5000
1!
1#
#10000
0!
0#
#15000
1!
1#
#20000
0!
0"
0#
0$
#25000
1!
1#
b10 %
b10 (
b100 )
b1 *
b100100011 +
b100 B
b1 C
#30000
0!
0#
#35000
1!
1#
b100 %
b1010001010110 &
b100 (
b110 )
b10 *
b1010001010110 +
b1 ,
b100 -
b101 .
b110 /
b1 0
11
02
03
04
b0 7
b0 8
b1010110 :
b0 ;
b0 <
b110 B
b10 C
b1 E
b101 G
b110 H
b100 I
b1010001010110 L
b1010110 N
b1 R
#40000
0!
0#
#45000
1!
1#
b110 %
b110 (
b1000 )
b11 *
b1010001010110 +
b1000 B
b11 C
#50000
0!
0#
#55000
1!
1#
b1000 %
b10011001111000 &
b1000 (
b1010 )
b100 *
b10011001111000 +
b10 ,
b110 -
b111 .
b1000 /
b10 0
11
02
03
04
b0 7
b0 8
b1111000 :
b0 ;
b0 <
b1010 B
b100 C
b10 E
b111 G
b1000 H
b110 I
b10011001111000 L
b1111000 N
b10 R
#60000
0!
0#
#65000
1!
1#
b1010 %
b1010 (
b1100 )
b101 *
b10011001111000 +
b1100 B
b101 C
#70000
0!
0#
#75000
1!
1#
b1100 %
b11100010011010 &
b1100 (
b1110 )
b110 *
b11100010011010 +
b11 ,
b1000 -
b1001 .
b1010 /
b11 0
11
02
03
04
b0 7
b0 8
b1111111110011010 :
b0 ;
b0 <
b1110 B
b110 C
b11 E
b1001 G
b1010 H
b1000 I
b11100010011010 L
b1111111110011010 N
b11 R
#80000
0!
0#
#85000
1!
1#
b1110 %
b1110 (
b10000 )
b111 *
b11100010011010 +
b10000 B
b111 C
#90000
0!
0#
#95000
1!
1#
b10000 %
b100101010111100 &
b10000 (
b10010 )
b1000 *
b100101010111100 +
b100 ,
b1010 -
b1011 .
b1100 /
b100 0
11
02
03
04
b0 7
b0 8
b1111111110111100 :
b0 ;
b0 <
b10010 B
b1000 C
b100 E
b1011 G
b1100 H
b1010 I
b100101010111100 L
b1111111110111100 N
b100 R
#100000
0!
0#
#105000
1!
1#
b10010 %
b10010 (
b10100 )
b1001 *
b100101010111100 +
b10100 B
b1001 C
#110000
0!
0#
#115000
1!
1#
b10100 %
b0 &
b10100 (
b10110 )
b1010 *
b0 +
b0 ,
b0 -
b0 .
b0 /
b0 0
11
02
03
04
b0 7
b0 8
b0 :
b0 ;
b0 <
b10110 B
b1010 C
b0 E
b0 G
b0 H
b0 I
b0 L
b0 N
b0 R
#120000
0!
0#
#125000
1!
1#
b10110 %
b10110 (
b11000 )
b1011 *
b0 +
b11000 B
b1011 C
#130000
0!
0#
#135000
1!
1#
b11000 %
b11000 (
b11010 )
b1100 *
b0 +
b11010 B
b1100 C
#140000
0!
0#
#145000
1!
1#
b11010 %
b11010 (
b11100 )
b1101 *
b0 +
b11100 B
b1101 C
#150000
0!
0#
#155000
1!
1#
b11100 %
b11100 (
b11110 )
b1110 *
b0 +
b11110 B
b1110 C
#160000
0!
0#
#165000
1!
1#
b11110 %
b11110 (
b100000 )
b1111 *
b0 +
b100000 B
b1111 C
#170000
0!
0#
#175000
1!
1#
b100000 %
b100000 (
b100010 )
b10000 *
b0 +
b100010 B
b10000 C
#180000
0!
0#
#185000
1!
1#
b100010 %
b100010 (
b100100 )
b10001 *
b0 +
b100100 B
b10001 C
#190000
0!
0#
#195000
1!
1#
b100100 %
b100100 (
b100110 )
b10010 *
b0 +
b100110 B
b10010 C
#200000
0!
0#
#205000
1!
1#
b100110 %
b100110 (
b101000 )
b10011 *
b0 +
b101000 B
b10011 C
#210000
0!
0#
#215000
1!
1#
b101000 %
b101000 (
b101010 )
b10100 *
b0 +
b101010 B
b10100 C
#220000
0!
0#
#225000
1!
1#
b101010 %
b101010 (
b101100 )
b10101 *
b0 +
b101100 B
b10101 C
#230000
0!
0#
#235000
1!
1#
b101100 %
b101100 (
b101110 )
b10110 *
b0 +
b101110 B
b10110 C
#240000
0!
0#
#245000
1!
1#
b101110 %
b101110 (
b110000 )
b10111 *
b0 +
b110000 B
b10111 C
#250000
0!
0#
#255000
1!
1#
b110000 %
b110000 (
b110010 )
b11000 *
b0 +
b110010 B
b11000 C
#260000
0!
0#
#265000
1!
1#
b110010 %
b110010 (
b110100 )
b11001 *
b0 +
b110100 B
b11001 C
#270000
0!
0#
#275000
1!
1#
b110100 %
b110100 (
b110110 )
b11010 *
b0 +
b110110 B
b11010 C
#280000
0!
0#
#285000
1!
1#
b110110 %
b110110 (
b111000 )
b11011 *
b0 +
b111000 B
b11011 C
#290000
0!
0#
#295000
1!
1#
b111000 %
b111000 (
b111010 )
b11100 *
b0 +
b111010 B
b11100 C
#300000
0!
0#
#305000
1!
1#
b111010 %
b111010 (
b111100 )
b11101 *
b0 +
b111100 B
b11101 C
#310000
0!
0#
#315000
1!
1#
b111100 %
b111100 (
b111110 )
b11110 *
b0 +
b111110 B
b11110 C
#320000
0!
0#
#325000
1!
1#
b111110 %
b111110 (
b1000000 )
b11111 *
b0 +
b1000000 B
b11111 C
#330000
0!
0#
#335000
1!
1#
b1000000 %
b1000000 (
b1000010 )
b100000 *
b0 +
b1000010 B
b100000 C
#340000
0!
0#
#345000
1!
1#
b1000010 %
b1000010 (
b1000100 )
b100001 *
b0 +
b1000100 B
b100001 C
#350000
0!
0#
#355000
1!
1#
b1000100 %
b1000100 (
b1000110 )
b100010 *
b0 +
b1000110 B
b100010 C
#360000
0!
0#
#365000
1!
1#
b1000110 %
b1000110 (
b1001000 )
b100011 *
b0 +
b1001000 B
b100011 C
#370000
0!
0#
#375000
1!
1#
b1001000 %
b1001000 (
b1001010 )
b100100 *
b0 +
b1001010 B
b100100 C
#380000
0!
0#
#385000
1!
1#
b1001010 %
b1001010 (
b1001100 )
b100101 *
b0 +
b1001100 B
b100101 C
#390000
0!
0#
#395000
1!
1#
b1001100 %
b1001100 (
b1001110 )
b100110 *
b0 +
b1001110 B
b100110 C
#400000
0!
0#
#405000
1!
1#
b1001110 %
b1001110 (
b1010000 )
b100111 *
b0 +
b1010000 B
b100111 C
#410000
0!
0#
#415000
1!
1#
b1010000 %
b1010000 (
b1010010 )
b101000 *
b0 +
b1010010 B
b101000 C
#420000
0!
0#
#425000
1!
1#
b1010010 %
b1010010 (
b1010100 )
b101001 *
b0 +
b1010100 B
b101001 C
#430000
0!
0#
#435000
1!
1#
b1010100 %
b1010100 (
b1010110 )
b101010 *
b0 +
b1010110 B
b101010 C
#440000
0!
0#
#445000
1!
1#
b1010110 %
b1010110 (
b1011000 )
b101011 *
b0 +
b1011000 B
b101011 C
#450000
0!
0#
#455000
1!
1#
b1011000 %
b1011000 (
b1011010 )
b101100 *
b0 +
b1011010 B
b101100 C
#460000
0!
0#
#465000
1!
1#
b1011010 %
b1011010 (
b1011100 )
b101101 *
b0 +
b1011100 B
b101101 C
#470000
0!
0#
#475000
1!
1#
b1011100 %
b1011100 (
b1011110 )
b101110 *
b0 +
b1011110 B
b101110 C
#480000
0!
0#
#485000
1!
1#
b1011110 %
b1011110 (
b1100000 )
b101111 *
b0 +
b1100000 B
b101111 C
#490000
0!
0#
#495000
1!
1#
b1100000 %
b1100000 (
b1100010 )
b110000 *
b0 +
b1100010 B
b110000 C
#500000
0!
0#
#505000
1!
1#
b1100010 %
b1100010 (
b1100100 )
b110001 *
b0 +
b1100100 B
b110001 C
#510000
0!
0#
#515000
1!
1#
b1100100 %
b1100100 (
b1100110 )
b110010 *
b0 +
b1100110 B
b110010 C
#520000
0!
0#
#525000
1!
1#
b1100110 %
b1100110 (
b1101000 )
b110011 *
b0 +
b1101000 B
b110011 C
#530000
0!
0#
#535000
1!
1#
b1101000 %
b1101000 (
b1101010 )
b110100 *
b0 +
b1101010 B
b110100 C
#540000
0!
0#
#545000
1!
1#
b1101010 %
b1101010 (
b1101100 )
b110101 *
b0 +
b1101100 B
b110101 C
#550000
0!
0#
#555000
1!
1#
b1101100 %
b1101100 (
b1101110 )
b110110 *
b0 +
b1101110 B
b110110 C
#560000
0!
0#
#565000
1!
1#
b1101110 %
b1101110 (
b1110000 )
b110111 *
b0 +
b1110000 B
b110111 C
#570000
0!
0#
#575000
1!
1#
b1110000 %
b1110000 (
b1110010 )
b111000 *
b0 +
b1110010 B
b111000 C
#580000
0!
0#
#585000
1!
1#
b1110010 %
b1110010 (
b1110100 )
b111001 *
b0 +
b1110100 B
b111001 C
#590000
0!
0#
#595000
1!
1#
b1110100 %
b1110100 (
b1110110 )
b111010 *
b0 +
b1110110 B
b111010 C
#600000
0!
0#
#605000
1!
1#
b1110110 %
b1110110 (
b1111000 )
b111011 *
b0 +
b1111000 B
b111011 C
#610000
0!
0#
#615000
1!
1#
b1111000 %
b1111000 (
b1111010 )
b111100 *
b0 +
b1111010 B
b111100 C
#620000
0!
0#
#625000
1!
1#
b1111010 %
b1111010 (
b1111100 )
b111101 *
b0 +
b1111100 B
b111101 C
#630000
0!
0#
#635000
1!
1#
b1111100 %
b1111100 (
b1111110 )
b111110 *
b0 +
b1111110 B
b111110 C
#640000
0!
0#
#645000
1!
1#
b1111110 %
b1111110 (
b10000000 )
b111111 *
b0 +
b10000000 B
b111111 C
#650000
0!
0#
#655000
1!
1#
b10000000 %
b10000000 (
b10000010 )
b1000000 *
b0 +
b10000010 B
b1000000 C
#660000
0!
0#
#665000
1!
1#
b10000010 %
b10000010 (
b10000100 )
b1000001 *
b0 +
b10000100 B
b1000001 C
#670000
0!
0#
#675000
1!
1#
b10000100 %
b10000100 (
b10000110 )
b1000010 *
b0 +
b10000110 B
b1000010 C
#680000
0!
0#
#685000
1!
1#
b10000110 %
b10000110 (
b10001000 )
b1000011 *
b0 +
b10001000 B
b1000011 C
#690000
0!
0#
#695000
1!
1#
b10001000 %
b10001000 (
b10001010 )
b1000100 *
b0 +
b10001010 B
b1000100 C
#700000
0!
0#
#705000
1!
1#
b10001010 %
b10001010 (
b10001100 )
b1000101 *
b0 +
b10001100 B
b1000101 C
#710000
0!
0#
#715000
1!
1#
b10001100 %
b10001100 (
b10001110 )
b1000110 *
b0 +
b10001110 B
b1000110 C
#720000
0!
0#
#725000
1!
1#
b10001110 %
b10001110 (
b10010000 )
b1000111 *
b0 +
b10010000 B
b1000111 C
#730000
0!
0#
#735000
1!
1#
b10010000 %
b10010000 (
b10010010 )
b1001000 *
b0 +
b10010010 B
b1001000 C
#740000
0!
0#
#745000
1!
1#
b10010010 %
b10010010 (
b10010100 )
b1001001 *
b0 +
b10010100 B
b1001001 C
#750000
0!
0#
#755000
1!
1#
b10010100 %
b10010100 (
b10010110 )
b1001010 *
b0 +
b10010110 B
b1001010 C
#760000
0!
0#
#765000
1!
1#
b10010110 %
b10010110 (
b10011000 )
b1001011 *
b0 +
b10011000 B
b1001011 C
#770000
0!
0#
#775000
1!
1#
b10011000 %
b10011000 (
b10011010 )
b1001100 *
b0 +
b10011010 B
b1001100 C
#780000
0!
0#
#785000
1!
1#
b10011010 %
b10011010 (
b10011100 )
b1001101 *
b0 +
b10011100 B
b1001101 C
#790000
0!
0#
#795000
1!
1#
b10011100 %
b10011100 (
b10011110 )
b1001110 *
b0 +
b10011110 B
b1001110 C
#800000
0!
0#
#805000
1!
1#
b10011110 %
b10011110 (
b10100000 )
b1001111 *
b0 +
b10100000 B
b1001111 C
#810000
0!
0#
#815000
1!
1#
b10100000 %
b10100000 (
b10100010 )
b1010000 *
b0 +
b10100010 B
b1010000 C
#820000
0!
0#
#825000
1!
1#
b10100010 %
b10100010 (
b10100100 )
b1010001 *
b0 +
b10100100 B
b1010001 C
#830000
0!
0#
#835000
1!
1#
b10100100 %
b10100100 (
b10100110 )
b1010010 *
b0 +
b10100110 B
b1010010 C
#840000
0!
0#
#845000
1!
1#
b10100110 %
b10100110 (
b10101000 )
b1010011 *
b0 +
b10101000 B
b1010011 C
#850000
0!
0#
#855000
1!
1#
b10101000 %
b10101000 (
b10101010 )
b1010100 *
b0 +
b10101010 B
b1010100 C
#860000
0!
0#
#865000
1!
1#
b10101010 %
b10101010 (
b10101100 )
b1010101 *
b0 +
b10101100 B
b1010101 C
#870000
0!
0#
#875000
1!
1#
b10101100 %
b10101100 (
b10101110 )
b1010110 *
b0 +
b10101110 B
b1010110 C
#880000
0!
0#
#885000
1!
1#
b10101110 %
b10101110 (
b10110000 )
b1010111 *
b0 +
b10110000 B
b1010111 C
#890000
0!
0#
#895000
1!
1#
b10110000 %
b10110000 (
b10110010 )
b1011000 *
b0 +
b10110010 B
b1011000 C
#900000
0!
0#
#905000
1!
1#
b10110010 %
b10110010 (
b10110100 )
b1011001 *
b0 +
b10110100 B
b1011001 C
#910000
0!
0#
#915000
1!
1#
b10110100 %
b10110100 (
b10110110 )
b1011010 *
b0 +
b10110110 B
b1011010 C
#920000
0!
0#
#925000
1!
1#
b10110110 %
b10110110 (
b10111000 )
b1011011 *
b0 +
b10111000 B
b1011011 C
#930000
0!
0#
#935000
1!
1#
b10111000 %
b10111000 (
b10111010 )
b1011100 *
b0 +
b10111010 B
b1011100 C
#940000
0!
0#
#945000
1!
1#
b10111010 %
b10111010 (
b10111100 )
b1011101 *
b0 +
b10111100 B
b1011101 C
#950000
0!
0#
#955000
1!
1#
b10111100 %
b10111100 (
b10111110 )
b1011110 *
b0 +
b10111110 B
b1011110 C
#960000
0!
0#
#965000
1!
1#
b10111110 %
b10111110 (
b11000000 )
b1011111 *
b0 +
b11000000 B
b1011111 C
#970000
0!
0#
#975000
1!
1#
b11000000 %
b11000000 (
b11000010 )
b1100000 *
b0 +
b11000010 B
b1100000 C
#980000
0!
0#
#985000
1!
1#
b11000010 %
b11000010 (
b11000100 )
b1100001 *
b0 +
b11000100 B
b1100001 C
#990000
0!
0#
#995000
1!
1#
b11000100 %
b11000100 (
b11000110 )
b1100010 *
b0 +
b11000110 B
b1100010 C
